Metadata-Version: 2.1
Name: libpython-jfobatista
Version: 0.2
Summary: Módulo de construção de projetos Python
Home-page: https://github.com/jfobatista/libpython
Author: João Francisco de Oliveira Batista
Author-email: jonesjoao_@hotmail.com
License:                     GNU GENERAL PUBLIC LICENSE
Platform: UNKNOWN
Classifier: Development Status :: 2 - Pre-Alpha
Classifier: Environment :: Console
Classifier: Intended Audience :: Developers
Classifier: License :: OSI Approved :: GNU Affero General Public License v3 or later (AGPLv3+)
Classifier: Operating System :: OS Independent
Classifier: Programming Language :: Python
Classifier: Programming Language :: Python :: 3.8
Classifier: Framework :: Pytest
License-File: LICENSE
